{
  "main": {
    "id": "5b8962a7662302a0",
    "type": "split",
    "children": [
      {
        "id": "45768f7b9c9ff383",
        "type": "tabs",
        "children": [
          {
            "id": "078e97aa6c1984af",
            "type": "leaf",
            "state": {
              "type": "markdown",
              "state": {
                "file": "Accu on sea 2026/Accu on Sea 2026 Notes.md",
                "mode": "source",
                "source": false
              },
              "icon": "lucide-file",
              "title": "Accu on Sea 2026 Notes"
            }
          },
          {
            "id": "48d61ea36c693e25",
            "type": "leaf",
            "state": {
              "type": "markdown",
              "state": {
                "file": "Accu on sea 2026/Accu on Sea 2026 Notes.md",
                "mode": "source",
                "source": false
              },
              "icon": "lucide-file",
              "title": "Accu on Sea 2026 Notes"
            }
          },
          {
            "id": "ea50a4d7a85e184e",
            "type": "leaf",
            "state": {
              "type": "markdown",
              "state": {
                "file": "Accu on sea 2026/Accu on Sea 2026 Notes.md",
                "mode": "source",
                "source": false
              },
              "icon": "lucide-file",
              "title": "Accu on Sea 2026 Notes"
            }
          },
          {
            "id": "c1f5a993058b958b",
            "type": "leaf",
            "state": {
              "type": "markdown",
              "state": {
                "file": "Accu on sea 2026/Accu on Sea 2026 Notes.md",
                "mode": "source",
                "source": false
              },
              "icon": "lucide-file",
              "title": "Accu on Sea 2026 Notes"
            }
          }
        ],
        "currentTab": 3
      }
    ],
    "direction": "vertical"
  },
  "left": {
    "id": "2d3f46e0ac18a01f",
    "type": "mobile-drawer",
    "children": [
      {
        "id": "58677b05ed2dcdca",
        "type": "leaf",
        "state": {
          "type": "file-explorer",
          "state": {
            "sortOrder": "alphabetical",
            "autoReveal": false
          },
          "icon": "lucide-folder-closed",
          "title": "Files"
        }
      },
      {
        "id": "5d20f6e965632e40",
        "type": "leaf",
        "state": {
          "type": "search",
          "state": {
            "query": "",
            "matchingCase": false,
            "explainSearch": false,
            "collapseAll": false,
            "extraContext": false,
            "sortOrder": "alphabetical"
          },
          "icon": "lucide-search",
          "title": "Search"
        }
      },
      {
        "id": "2a828917610420c2",
        "type": "leaf",
        "state": {
          "type": "tag",
          "state": {
            "sortOrder": "frequency",
            "useHierarchy": true,
            "showSearch": false,
            "searchQuery": ""
          },
          "icon": "lucide-tags",
          "title": "Tags"
        }
      },
      {
        "id": "3d1a591ad8bf99bd",
        "type": "leaf",
        "state": {
          "type": "all-properties",
          "state": {
            "sortOrder": "frequency",
            "showSearch": false,
            "searchQuery": ""
          },
          "icon": "lucide-archive",
          "title": "All properties"
        }
      },
      {
        "id": "c8cb2d38693638be",
        "type": "leaf",
        "state": {
          "type": "bookmarks",
          "state": {},
          "icon": "lucide-bookmark",
          "title": "Bookmarks"
        }
      }
    ],
    "currentTab": 0
  },
  "right": {
    "id": "40c4ea2b62dc05fc",
    "type": "mobile-drawer",
    "children": [
      {
        "id": "910eb7322dbbe708",
        "type": "leaf",
        "state": {
          "type": "backlink",
          "state": {
            "file": "Accu on sea 2026/Accu on Sea 2026 Notes.md",
            "collapseAll": false,
            "extraContext": false,
            "sortOrder": "alphabetical",
            "showSearch": false,
            "searchQuery": "",
            "backlinkCollapsed": false,
            "unlinkedCollapsed": true
          },
          "icon": "links-coming-in",
          "title": "Backlinks"
        }
      },
      {
        "id": "101fc2f91c70f22d",
        "type": "leaf",
        "state": {
          "type": "outgoing-link",
          "state": {
            "file": "Accu on sea 2026/Accu on Sea 2026 Notes.md",
            "linksCollapsed": false,
            "unlinkedCollapsed": true
          },
          "icon": "links-going-out",
          "title": "Outgoing links"
        }
      },
      {
        "id": "657315f4364dc124",
        "type": "leaf",
        "state": {
          "type": "outline",
          "state": {
            "file": "Accu on sea 2026/Accu on sea notes.md",
            "followCursor": false,
            "showSearch": false,
            "searchQuery": ""
          },
          "icon": "lucide-list",
          "title": "Outline"
        }
      }
    ],
    "currentTab": 1
  },
  "left-ribbon": {
    "hiddenItems": {
      "switcher:Open quick switcher": false,
      "graph:Open graph view": false,
      "canvas:Create new canvas": false,
      "daily-notes:Open today's daily note": false,
      "templates:Insert template": false,
      "command-palette:Open command palette": false,
      "bases:Create new base": false
    }
  },
  "active": "c1f5a993058b958b",
  "lastOpenFiles": [
    "Accu on sea 2026/Arrival on Tuesday.md",
    "Accu on sea 2026/().md",
    "Accu on sea 2026/Accu on Sea 2026 Notes.md",
    "Accu on sea 2026/Route.md",
    "Schedule Wednesday.md",
    "Overview.md",
    "More links.md",
    "src/gutenberg/block.txt",
    "src/gutenberg",
    "src",
    "Accu on sea 2026/Need for guidelines.md",
    "Accu on sea 2026/Shoppinglist.md",
    "Untitled 1.md",
    "Accu on sea 2026/images/IMG_20260613_004702.jpg",
    "Accu on sea 2026/images/IMG_20260612_225734.jpg",
    "Accu on sea 2026/images/IMG_20260612_225734 1.jpg",
    "Accu on sea 2026/images",
    "80ab52aaced346c8b7a0d110f00671c8.jpg",
    "Accu on sea 2026"
  ]
}